.pypirc
MANIFEST.in
__init__.py
hi.txt
in.sh
rm.sh
setup.py
test.txt
cc42/__init__.py
cc42/cc42.py
cc42.egg-info/PKG-INFO
cc42.egg-info/SOURCES.txt
cc42.egg-info/dependency_links.txt
cc42.egg-info/entry_points.txt
cc42.egg-info/not-zip-safe
cc42.egg-info/requires.txt
cc42.egg-info/top_level.txt