Metadata-Version: 1.0
Name: cc42
Version: 0.0.2
Summary: 
Home-page: http://42qu.cc/:help
Author: 42qu.com 42区
Author-email: admin@42qu.com
License: UNKNOWN
Platform: UNKNOWN
